streamlit_tetrascience_ui/__init__.py
streamlit_tetrascience_ui/py_components/__init__.py
streamlit_tetrascience_ui/py_components/button_component.py
streamlit_tetrascience_ui/py_components/example.py
streamlit_tetrascience_ui/py_components/histogram_component.py
streamlit_tetrascience_ui/py_components/my_component.py
streamlit_tetrascience_ui/py_components/containers/__init__.py
streamlit_tetrascience_ui/py_components/utils/__init__.py
streamlit_tetrascience_ui/py_components/utils/callback.py
streamlit_tetrascience_ui/py_components/utils/declare.py
streamlit_tetrascience_ui/py_components/utils/session.py
streamlit_tetrascience_ui-0.1.1.dist-info/licenses/LICENSE
streamlit_tetrascience_ui-0.1.1.dist-info/METADATA
streamlit_tetrascience_ui-0.1.1.dist-info/WHEEL
streamlit_tetrascience_ui-0.1.1.dist-info/top_level.txt
streamlit_tetrascience_ui-0.1.1.dist-info/RECORD
