Metadata-Version: 2.4
Name: streamlit-tetrascience-ui
Version: 0.1.1
Summary: Tetrascience UI components for Streamlit
Home-page: https://github.com/vulcancreative/tetrascience-python
Author: Vulcan at Tetrascience
Author-email: Vulcan at Tetrascience <dev@vulcan.agency>
Project-URL: homepage, https://github.com/vulcancreative/tetrascience-python
Project-URL: repository, https://github.com/vulcancreative/tetrascience-python
Keywords: streamlit,tetrascience,ui,components
Classifier: Programming Language :: Python :: 3
Classifier: License :: OSI Approved :: MIT License
Classifier: Operating System :: OS Independent
Requires-Python: >=3.9
License-File: LICENSE
Requires-Dist: streamlit
Dynamic: author
Dynamic: home-page
Dynamic: license-file
Dynamic: requires-python
